src/16bit-cpu/src/mem/data_mem.v
// src/mem/data_mem.v
module data_mem (
    input  wire        clk,
    input  wire [15:0] addr,
    input  wire [15:0] wdata,
    output reg  [15:0] rdata,
    input  wire        we
);
    reg [15:0] ram [0:15];  // 16 kelimelik küçük RAM

    // Okuma: kombi
    always @* begin
        rdata = ram[addr[3:0]];  // 4-bit adres
    end

    // Yazma: senkron
    always @(posedge clk) begin
        if (we) begin
            ram[addr[3:0]] <= wdata;  // 4-bit adres
        end
    end

endmodule

src/16bit-cpu/src/mem/instr_mem.v
// src/mem/instr_mem.v
module instr_mem (
    input  wire [15:0] addr,
    output reg  [15:0] data
);
    // Opcode sabitleri
    localparam OP_NOP   = 4'b0000;
    localparam OP_LDI   = 4'b0001;
    localparam OP_ADDI  = 4'b0010;
    localparam OP_LOAD  = 4'b0011;
    localparam OP_STORE = 4'b0100;
    localparam OP_HALT  = 4'b1111;

    always @* begin
        case (addr[7:0])
            8'd0: data = {OP_LDI,   12'h005}; // ACC = 5
            8'd1: data = {OP_ADDI,  12'h00A}; // ACC += 10 -> 15
            8'd2: data = {OP_STORE, 12'h00F}; // MEM[0x0F] = 15 (adres 15)
            8'd3: data = {OP_LDI,   12'h000}; // ACC = 0
            8'd4: data = {OP_LOAD,  12'h00F}; // ACC = MEM[0x0F] -> 15
            8'd5: data = {OP_HALT,  12'h000};
            default: data = {OP_NOP, 12'h000};
        endcase
    end

endmodule

src/16bit-cpu/src/cpu/alu.v
// src/cpu/alu.v
module alu16 (
    input  wire [15:0] a,
    input  wire [15:0] b,
    input  wire [2:0]  op,    // ALU operation select
    output reg  [15:0] y,
    output wire        zero
);
    // ALU op kodları
    localparam ALU_ADD  = 3'b000;
    localparam ALU_SUB  = 3'b001;
    localparam ALU_AND  = 3'b010;
    localparam ALU_OR   = 3'b011;
    localparam ALU_XOR  = 3'b100;
    localparam ALU_PASS = 3'b101; // sadece b'yi geçir

    always @* begin
        case (op)
            ALU_ADD:  y = a + b;
            ALU_SUB:  y = a - b;
            ALU_AND:  y = a & b;
            ALU_OR:   y = a | b;
            ALU_XOR:  y = a ^ b;
            ALU_PASS: y = b;
            default:  y = 16'h0000;
        endcase
    end

    assign zero = (y == 16'h0000);

endmodule

src/16bit-cpu/src/cpu/simple16_cpu.v
// src/cpu/simple16_cpu.v

// src/cpu/simple16_cpu.v

module simple16_cpu (
    input  wire        clk,
    input  wire        reset,

    // Instruction memory (read-only arayüz)
    output wire [15:0] imem_addr,
    input  wire [15:0] imem_data,

    // Data memory (read/write arayüz)
    output reg  [15:0] dmem_addr,
    output reg  [15:0] dmem_wdata,
    input  wire [15:0] dmem_rdata,
    output reg         dmem_we,

    // Debug/durum
    output wire        halted,
    output wire [15:0] acc_out,
    output wire [15:0] pc_out
);

    // Ana register'lar
    reg [15:0] pc;
    reg [15:0] acc;
    reg        halted_r;

    assign halted = halted_r;
    assign acc_out = acc;
    assign pc_out  = pc;

    assign imem_addr = pc;

    // Instruction alanları
    wire [3:0]  opcode  = imem_data[15:12];
    wire [11:0] operand = imem_data[11:0];
    wire [15:0] op_ext  = {4'b0000, operand};

    // ALU
    reg  [2:0]  alu_op;
    wire [15:0] alu_y;
    wire        alu_zero;

    alu16 alu_inst (
        .a(acc),
        .b(op_ext),
        .op(alu_op),
        .y(alu_y),
        .zero(alu_zero)
    );

    // Opcode sabitleri
    localparam OP_NOP   = 4'b0000;
    localparam OP_LDI   = 4'b0001;
    localparam OP_ADDI  = 4'b0010;
    localparam OP_LOAD  = 4'b0011;
    localparam OP_STORE = 4'b0100;
    localparam OP_HALT  = 4'b1111;

    // Next-state sinyalleri
    reg [15:0] next_pc;
    reg [15:0] next_acc;
    reg        next_halted;

    reg        next_dmem_we;
    reg [15:0] next_dmem_addr;
    reg [15:0] next_dmem_wdata;

    // Kombinasyonel kontrol
    always @* begin
        // Varsayılanlar: bir şey yapma
        next_pc       = pc;
        next_acc      = acc;
        next_halted   = halted_r;

        next_dmem_we    = 1'b0;
        next_dmem_addr  = dmem_addr;
        next_dmem_wdata = dmem_wdata;

        alu_op = 3'b101; // default PASS (şimdilik LDI için kullanacağız)

        if (!halted_r) begin
            // Default: PC bir sonrakine geçsin
            next_pc = pc + 16'd1;

            case (opcode)
                OP_NOP: begin
                    // hi̇çbi̇r şey yapma
                end

                OP_LDI: begin
                    // ACC <- imm
                    alu_op  = 3'b101;   // PASS B
                    next_acc = op_ext;  // direkt immediate
                end

                OP_ADDI: begin
                    // ACC <- ACC + imm
                    alu_op   = 3'b000;  // ADD
                    next_acc = alu_y;
                end

                OP_LOAD: begin
                    // ACC <- MEM[addr]
                    next_dmem_addr = op_ext;
                    // data_mem combinational read varsayıyoruz
                    next_acc       = dmem_rdata;
                end

                OP_STORE: begin
                    // MEM[addr] <- ACC
                    next_dmem_addr  = op_ext;
                    next_dmem_wdata = acc;
                    next_dmem_we    = 1'b1;
                end

                OP_HALT: begin
                    next_halted = 1'b1;
                end

                default: begin
                    // tanımsız → NOP gibi
                end
            endcase
        end
    end

    // Senkron state güncelleme
    always @(posedge clk or posedge reset) begin
        if (reset) begin
            pc        <= 16'd0;
            acc       <= 16'd0;
            halted_r  <= 1'b0;

            dmem_we    <= 1'b0;
            dmem_addr  <= 16'd0;
            dmem_wdata <= 16'd0;
        end else begin
            pc        <= next_pc;
            acc       <= next_acc;
            halted_r  <= next_halted;

            dmem_we    <= next_dmem_we;
            dmem_addr  <= next_dmem_addr;
            dmem_wdata <= next_dmem_wdata;
        end
    end

endmodule

src/16bit-cpu/src/top/simple16_system.v
// src/top/simple16_system.v
module simple16_system (
    input  wire clk,
    input  wire reset,
    output wire halted,
    output wire [15:0] acc_out
);
    wire [15:0] pc;
    wire [15:0] imem_data;

    wire [15:0] dmem_addr;
    wire [15:0] dmem_wdata;
    wire [15:0] dmem_rdata;
    wire        dmem_we;

    simple16_cpu cpu_inst (
        .clk        (clk),
        .reset      (reset),
        .imem_addr  (pc),
        .imem_data  (imem_data),
        .dmem_addr  (dmem_addr),
        .dmem_wdata (dmem_wdata),
        .dmem_rdata (dmem_rdata),
        .dmem_we    (dmem_we),
        .halted     (halted),
        .acc_out    (acc_out),
        .pc_out     ()
    );

    instr_mem imem_inst (
        .addr (pc),
        .data (imem_data)
    );

    data_mem dmem_inst (
        .clk   (clk),
        .addr  (dmem_addr),
        .wdata (dmem_wdata),
        .rdata (dmem_rdata),
        .we    (dmem_we)
    );

endmodule

src/16bit-cpu/tb/simple16_system_tb.v
// src/tb/simple16_system_tb.v
`timescale 1ns/1ps

module simple16_system_tb;
    initial begin
        $dumpfile("wave.vcd");
        $dumpvars(0, simple16_system_tb);
    end

    reg clk;
    reg reset;

    wire halted;
    wire [15:0] acc_out;

    // Test edilen sistem
    simple16_system dut (
        .clk    (clk),
        .reset  (reset),
        .halted (halted),
        .acc_out(acc_out)
    );

    // Clock üretimi: 10ns period → 100 MHz
    initial begin
        clk = 0;
        forever #5 clk = ~clk;
    end

    // Test senaryosu
    initial begin
        $display("Test basliyor...");

        reset = 1;
        #20;
        reset = 0;

        // Maks 200 ns bekleyelim
        wait (halted == 1'b1 || $time > 2000);

        $display("Sim sonu: time=%0t ns, halted=%b, ACC=%0d (0x%04h)",
                 $time, halted, acc_out, acc_out);

        if (halted && acc_out == 16'd15) begin
            $display("TEST OK: ACC=15 bekledigimiz gibi.");
        end else begin
            $display("TEST FAIL: ACC beklenenden farkli.");
        end

        #20;
        $finish;
    end
endmodule

src/16bit-cpu/wave.vcd
$date
	Mon Dec  8 11:30:46 2025
$end
$version
	Icarus Verilog
$end
$timescale
	1ps
$end
$scope module simple16_system_tb $end
$var wire 1 ! halted $end
$var wire 16 " acc_out [15:0] $end
$var reg 1 # clk $end
$var reg 1 $ reset $end
$scope module dut $end
$var wire 1 # clk $end
$var wire 1 $ reset $end
$var wire 16 % pc [15:0] $end
$var wire 16 & imem_data [15:0] $end
$var wire 1 ! halted $end
$var wire 1 ' dmem_we $end
$var wire 16 ( dmem_wdata [15:0] $end
$var wire 16 ) dmem_rdata [15:0] $end
$var wire 16 * dmem_addr [15:0] $end
$var wire 16 + acc_out [15:0] $end
$scope module cpu_inst $end
$var wire 16 , acc_out [15:0] $end
$var wire 1 # clk $end
$var wire 1 ! halted $end
$var wire 16 - imem_addr [15:0] $end
$var wire 16 . pc_out [15:0] $end
$var wire 1 $ reset $end
$var wire 12 / operand [11:0] $end
$var wire 4 0 opcode [3:0] $end
$var wire 16 1 op_ext [15:0] $end
$var wire 16 2 imem_data [15:0] $end
$var wire 16 3 dmem_rdata [15:0] $end
$var wire 1 4 alu_zero $end
$var wire 16 5 alu_y [15:0] $end
$var parameter 4 6 OP_ADDI $end
$var parameter 4 7 OP_HALT $end
$var parameter 4 8 OP_LDI $end
$var parameter 4 9 OP_LOAD $end
$var parameter 4 : OP_NOP $end
$var parameter 4 ; OP_STORE $end
$var reg 16 < acc [15:0] $end
$var reg 3 = alu_op [2:0] $end
$var reg 16 > dmem_addr [15:0] $end
$var reg 16 ? dmem_wdata [15:0] $end
$var reg 1 ' dmem_we $end
$var reg 1 @ halted_r $end
$var reg 16 A next_acc [15:0] $end
$var reg 16 B next_dmem_addr [15:0] $end
$var reg 16 C next_dmem_wdata [15:0] $end
$var reg 1 D next_dmem_we $end
$var reg 1 E next_halted $end
$var reg 16 F next_pc [15:0] $end
$var reg 16 G pc [15:0] $end
$scope module alu_inst $end
$var wire 16 H a [15:0] $end
$var wire 16 I b [15:0] $end
$var wire 3 J op [2:0] $end
$var wire 1 4 zero $end
$var parameter 3 K ALU_ADD $end
$var parameter 3 L ALU_AND $end
$var parameter 3 M ALU_OR $end
$var parameter 3 N ALU_PASS $end
$var parameter 3 O ALU_SUB $end
$var parameter 3 P ALU_XOR $end
$var reg 16 Q y [15:0] $end
$upscope $end
$upscope $end
$scope module dmem_inst $end
$var wire 16 R addr [15:0] $end
$var wire 1 # clk $end
$var wire 16 S wdata [15:0] $end
$var wire 1 ' we $end
$var reg 16 T rdata [15:0] $end
$upscope $end
$scope module imem_inst $end
$var wire 16 U addr [15:0] $end
$var parameter 4 V OP_ADDI $end
$var parameter 4 W OP_HALT $end
$var parameter 4 X OP_LDI $end
$var parameter 4 Y OP_LOAD $end
$var parameter 4 Z OP_NOP $end
$var parameter 4 [ OP_STORE $end
$var reg 16 \ data [15:0] $end
$upscope $end
$upscope $end
$upscope $end
$enddefinitions $end
$comment Show the parameter values. $end
$dumpall
b100 [
b0 Z
b11 Y
b1 X
b1111 W
b10 V
b100 P
b1 O
b101 N
b11 M
b10 L
b0 K
b100 ;
b0 :
b11 9
b1 8
b1111 7
b10 6
$end
#0
$dumpvars
b1000000000101 \
b0 U
bx T
b0 S
b0 R
b101 Q
b101 J
b101 I
b0 H
b0 G
b1 F
0E
0D
b0 C
b0 B
b101 A
0@
b0 ?
b0 >
b101 =
b0 <
b101 5
04
bx 3
b1000000000101 2
b101 1
b1 0
b101 /
b0 .
b0 -
b0 ,
b0 +
b0 *
bx )
b0 (
0'
b1000000000101 &
b0 %
1$
0#
b0 "
0!
$end
#5000
1#
#10000
0#
#15000
1#
#20000
0#
0$
#25000
b1111 A
b1111 5
b1111 Q
b0 =
b0 J
b1010 1
b1010 I
b1010 /
b10 0
b10 F
b10000000001010 &
b10000000001010 2
b10000000001010 \
b101 "
b101 +
b101 ,
b101 <
b101 H
b1 %
b1 -
b1 U
b1 .
b1 G
1#
#30000
0#
#35000
1D
b1111 C
b10000 B
b10000 1
b10000 I
b10000 /
b100 0
b10000 5
b10000 Q
b11 F
b101 =
b101 J
b100000000010000 &
b100000000010000 2
b100000000010000 \
b1111 "
b1111 +
b1111 ,
b1111 <
b1111 H
b10 %
b10 -
b10 U
b10 .
b10 G
1#
#40000
0#
#45000
14
b0 5
b0 Q
b0 A
b0 1
b0 I
b0 /
b1 0
b100 F
0D
b1000000000000 &
b1000000000000 2
b1000000000000 \
b1111 (
b1111 ?
b1111 S
b10000 *
b10000 >
b10000 R
1'
b11 %
b11 -
b11 U
b11 .
b11 G
1#
#50000
0#
#55000
04
b10000 5
b10000 Q
b1111 A
b10000 1
b10000 I
b10000 /
b11 0
b101 F
b11000000010000 &
b11000000010000 2
b11000000010000 \
b1111 )
b1111 3
b1111 T
0'
b0 "
b0 +
b0 ,
b0 <
b0 H
b100 %
b100 -
b100 U
b100 .
b100 G
1#
#60000
0#
#65000
14
b0 5
b0 Q
1E
b0 1
b0 I
b0 /
b1111 0
b110 F
b1111000000000000 &
b1111000000000000 2
b1111000000000000 \
b1111 "
b1111 +
b1111 ,
b1111 <
b1111 H
b101 %
b101 -
b101 U
b101 .
b101 G
1#
#70000
0#
#75000
b0 0
b0 &
b0 2
b0 \
1!
1@
b110 %
b110 -
b110 U
b110 .
b110 G
1#
